{
    "source": "H\u00e4ndische Erfassung mit Beizug der Literatur",
    "data": [
        {
            "lat": "46.798449",
            "lon": "8.231879",
            "population": 8738791,
            "country": "CH",
            "name": "Switzerland",
            "osm_id": 1682079
        },
        {
            "lat": "49.777222",
            "lon": "6.095278",
            "population": 660809,
            "country": "LU",
            "name": "Luxembourg",
            "osm_id": 1682079
        }
    ]
}